py2annotate/__init__.py
py2annotate-1.1.1.dist-info/METADATA
py2annotate-1.1.1.dist-info/RECORD
py2annotate-1.1.1.dist-info/WHEEL
py2annotate-1.1.1.dist-info/top_level.txt
