Metadata-Version: 2.1
Name: py2annotate
Version: 1.1.1
Summary: An extension to Sphinx :code:`autodoc` to augment Sphinx documentation with type annotations, when using Python 2 style type annotations.
Home-page: https://github.com/patrick-kidger/py2annotate
Author: Patrick Kidger
Author-email: contact@kidger.site
Maintainer: Patrick Kidger
Maintainer-email: contact@kidger.site
License: Apache-2.0
Keywords: signature
Platform: UNKNOWN
Classifier: Development Status :: 4 - Beta
Classifier: Environment :: Web Environment
Classifier: Framework :: Sphinx
Classifier: Framework :: Sphinx :: Extension
Classifier: Intended Audience :: Developers
Classifier: Intended Audience :: Education
Classifier: Intended Audience :: End Users/Desktop
Classifier: Intended Audience :: Science/Research
Classifier: Intended Audience :: System Administrators
Classifier: License :: OSI Approved :: Apache Software License
Classifier: Natural Language :: English
Classifier: Operating System :: OS Independent
Classifier: Programming Language :: Python :: 3
Classifier: Programming Language :: Python :: 3.6
Classifier: Programming Language :: Python :: 3.7
Classifier: Programming Language :: Python :: 3.8
Classifier: Programming Language :: Python :: 3 :: Only
Classifier: Topic :: Documentation
Classifier: Topic :: Documentation :: Sphinx
Classifier: Topic :: Internet :: WWW/HTTP :: Site Management
Classifier: Topic :: Software Development :: Documentation
Requires-Python: >=3.6
Requires-Dist: sphinx
Requires-Dist: mypy
